asyncwago/__init__.py
asyncwago/server.py
asyncwago-0.31.7.dist-info/licenses/LICENSE
tests/__init__.py
tests/conftest.py
tests/test_mockserver.py
asyncwago-0.31.7.dist-info/METADATA
asyncwago-0.31.7.dist-info/WHEEL
asyncwago-0.31.7.dist-info/top_level.txt
asyncwago-0.31.7.dist-info/RECORD
